<annotation>
	<folder>collectedimages</folder>
	<filename>hello.f12cfc8f-33e3-11ec-9384-9a87491bdce2.jpg</filename>
	<path>C:\Users\aishw\RealTimeObjectDetection\Tensorflow\workspace\images\collectedimages\hello.f12cfc8f-33e3-11ec-9384-9a87491bdce2.jpg</path>
	<source>
		<database>Unknown</database>
	</source>
	<size>
		<width>640</width>
		<height>480</height>
		<depth>3</depth>
	</size>
	<segmented>0</segmented>
	<object>
		<name>hello</name>
		<pose>Unspecified</pose>
		<truncated>0</truncated>
		<difficult>0</difficult>
		<bndbox>
			<xmin>343</xmin>
			<ymin>139</ymin>
			<xmax>602</xmax>
			<ymax>374</ymax>
		</bndbox>
	</object>
</annotation>
